Workbook

Sheet README
C1: 注意这个文档不能 merge！！ 发现冲突以后，先备份自己的改动，然后更新到最新版，然后再添加新的数据。
C3: 正式的数据从第二个 sheet 页开始,每页 从 D7 单元格开始有效 同一个表的数据要连续,中间不能有空行 Sheet 页的名字不要包含空格,中文等 | E3: 颜色示例(非必须,非强制)
C4: 请给特殊单元格,列名添加颜色,提高数据可读性 | E4: *自动生成 | F4: #唯一性检查 | G4: 公式=外键引用
C5: 理论上,表的前后顺序,sheet 页的顺序没有严格要求,但请尽量按照先插 后引用的顺序排列,减少迭代次数!
C7: 列名格式举例 | D7: 说明 | E7: 备注
C8: ROLE_CODE | D8: 普通
C9: *USER_ID | D9: *前置, 该列的值自动生成,当数据库存在等价记录时,这个值会被替换为数据库中已存在的值 | E9: 自增长(或序列)主键列. 当不作为外键引用时,一般写* 作为外键时,写可读的值 | F9: 目前 oracle 是序列,其他自增涨
C10: #USER_NAME | D10: #前置,表中所有带有#的列组成一个唯一性校验,在执行插入之前,会首先按照唯一键来检查数据库是否存在等价记录 | E10: 可以有多列.仅支持数字,字符串 当#列涉及到公式时,会先确定公式的值
C11: UNIT_PRICE(DECIMAL) | D11: (TYPE)指定这一列的类型,默认会自动检测: _ID结尾为数字; _DATE 结尾为日期; 其他默认为VARCHAR | E11: 一般不需要指定. 日期格式仅支持: yyyy-MM-dd HH:mm:ss yyyy-MM-dd
C12: ROLE_NAME:zh_CN | D12: :LANG 指定语言环境 | E12: TL 表数据不需要专门写
C15: 外键引用(公式) | D15: 用于引用外键,也可用于普通值 目前不支持特别复杂的公式 | E15: 自动增长列,如果被公式引用,最好写一个人可以读懂的值,增强公式可读性
C18: 关于公式的说明
C19: 一般用于引用自动生成的外键.所有公式均为 Excel 支持的标准公式,但不支持特别复杂的计算公式,比如范围计算
C20: E9 | D20: 相对引用当前页 E9 单元格
C21: $E$9 | D21: 绝对引用当前页 E9 单元格
C22: RESOURCE!E23 | D22: 引用 RESOURCE 页的 E23 单元格(相对)
C23: RESOURCE!$E$23 | D23: 引用 RESOURCE 页的 E23 单元格(绝对)
C25: 关于相对引用 | D25: 举例:当 F10 单元格引用 A9 时 将 F10 的复制到 F11 单元格时, F11 引用的是 A10 将 F10 的复制到 G11 时, G11 实际引用的是 B10 以上情况适用于拖拽填充
C26: 关于绝对引用 | D26: 复制公式单元格时,保持公式不变
C27: 相对引用,绝对引用各有用途. 直接拖拽填充就可以避免大量重复工作

Sheet 服务注册
A1: 日期 | B1: 作者 | C1: 说明 | D1: 表
E4: *自动生成 | F4: #唯一性检查 | G4: 公式=外键引用
A7: 2020-07-06 | B7: hzero | C7: 服务配置 | D7: hitf_interface_server | E7: *interface_server_id | F7: #tenant_id | G7: #server_code | H7: server_name | I7: service_type | J7: domain_url | K7: soap_namespace | L7: soap_element_prefix | M7: enabled_flag | N7: service_category | O7: namespace | P7: enabled_certificate_flag | Q7: certificate_id | R7: swagger_url | S7: public_flag
E8: hitf_interface_server-8 | F8: 0 | G8: HIVC | H8: 发票服务 | I8: REST | M8: 1 | N8: COMPOSITE | O8: HZERO | P8: 0 | S8: 0
E9: hitf_interface_server-9 | F9: 0 | G9: HIVC.HANGXIN | H9: 航信发票服务 | I9: REST | J9: http://192.168.17.180:8080/inv/invoice/api | M9: 1 | N9: EXTERNAL | O9: HZERO | P9: 0 | S9: 0
E10: hitf_interface_server-10 | F10: 0 | G10: HIVC.HELIOS | H10: 汇联易发票服务 | I10: REST | J10: http://106.15.26.10:10080 | M10: 1 | N10: EXTERNAL | O10: HZERO | P10: 0 | S10: 0

Sheet 接口配置
A1: 日期 | B1: 作者 | C1: 说明 | D1: 表
E4: *自动生成 | F4: #唯一性检查 | G4: 公式=外键引用
A7: 2020-07-06 | B7: hzero | C7: 接口配置 | D7: hitf_interface | E7: *interface_id | F7: tenant_id | G7: #interface_server_id | H7: #interface_code | I7: interface_name | J7: interface_url | K7: publish_type | L7: request_method | M7: request_header | N7: enabled_flag | O7: soap_version | P7: soap_action | Q7: status | R7: remark | S7: mapping_class
E8: hitf_interface-8 | F8: 0 | G8: =服务注册!$E$8 | H8: INVOICE_AUTH | I8: 发票认证 | K8: REST | L8: POST | M8: application/json | N8: 1 | Q8: NEW
E9: hitf_interface-9 | F9: 0 | G9: =服务注册!$E$8 | H9: INVOICE_AUTH_RESULT | I9: 发票认证结果查询 | K9: REST | L9: POST | M9: application/json | N9: 1 | Q9: NEW
E10: hitf_interface-10 | F10: 0 | G10: =服务注册!$E$8 | H10: INVOICE_CHECK | I10: 发票查验 | K10: REST | L10: POST | M10: application/json | N10: 1 | Q10: NEW
E11: hitf_interface-11 | F11: 0 | G11: =服务注册!$E$8 | H11: INVOICE_META_DATA | I11: 发票主数据采集 | K11: REST | L11: POST | M11: application/json | N11: 1 | Q11: NEW
E12: hitf_interface-12 | F12: 0 | G12: =服务注册!$E$8 | H12: INVOICE_TICK | I12: 发票勾选 | K12: REST | L12: POST | M12: application/json | N12: 1 | Q12: NEW
E13: hitf_interface-13 | F13: 0 | G13: =服务注册!$E$8 | H13: INVOICE_TICK_RESULT | I13: 发票勾选结果查询 | K13: REST | L13: POST | M13: application/json | N13: 1 | Q13: NEW
E14: hitf_interface-14 | F14: 0 | G14: =服务注册!$E$9 | H14: INVOICE_AUTH | I14: 发票认证 | J14: invoiceRequest | K14: REST | L14: POST | M14: application/json | N14: 1 | Q14: ENABLED
E15: hitf_interface-15 | F15: 0 | G15: =服务注册!$E$9 | H15: INVOICE_AUTH_RESULT | I15: 发票认证结果查询 | J15: /businessInfo | K15: REST | L15: POST | M15: application/json | N15: 1 | Q15: ENABLED
E16: hitf_interface-16 | F16: 0 | G16: =服务注册!$E$9 | H16: INVOICE_CHECK | I16: 发票查验 | J16: /invoiceCheck | K16: REST | L16: POST | M16: application/json | N16: 1 | Q16: ENABLED
E17: hitf_interface-17 | F17: 0 | G17: =服务注册!$E$9 | H17: INVOICE_META_DATA | I17: 发票主信息采集 | J17: /invoiceMainInfor | K17: REST | L17: POST | M17: application/json | N17: 1 | Q17: ENABLED
E18: hitf_interface-18 | F18: 0 | G18: =服务注册!$E$9 | H18: INVOICE_TICK | I18: 发票勾选 | J18: /invoiceCheckRequest | K18: REST | L18: POST | M18: application/json | N18: 1 | Q18: ENABLED
E19: hitf_interface-19 | F19: 0 | G19: =服务注册!$E$9 | H19: INVOICE_TICK_RESULT | I19: 发票勾选结果查询 | J19: /invoiceCheckRespond | K19: REST | L19: POST | M19: application/json | N19: 1 | Q19: ENABLED
E20: hitf_interface-20 | F20: 0 | G20: =服务注册!$E$10 | H20: HINVC | I20: 发票统一查验 | J20: /receipt/api/open/v1/verify | K20: REST | L20: POST | M20: application/json | N20: 1 | Q20: ENABLED
E21: hitf_interface-21 | F21: 0 | G21: =服务注册!$E$10 | H21: HOCR | I21: 发票图像识别 | J21: /receipt/api/open/v1/ocr | K21: REST | L21: POST | M21: application/json | N21: 1 | Q21: ENABLED

Sheet 服务认证配置
A1: 日期 | B1: 作者 | C1: 说明 | D1: 表
E4: *自动生成 | F4: #唯一性检查 | G4: 公式=外键引用
A7: 2020-07-06 | B7: hzero | C7: 接口认证管理 | D7: hitf_interface_auth | E7: *interface_auth_id | F7: #interface_id | G7: tenant_id | H7: #auth_level | I7: #auth_level_value | J7: auth_type | K7: grant_type | L7: access_token_url | M7: remark | N7: password_encode_type
E8: hitf_interface_auth-8 | G8: 0 | H8: SERVER | I8: =服务注册!$E$9 | J8: NONE
E9: hitf_interface_auth-9 | G9: 0 | H9: SERVER | I9: =服务注册!$E$10 | J9: NONE

Sheet 接口文档参数
A1: 日期 | B1: 作者 | C1: 说明 | D1: 表
E4: *自动生成 | F4: #唯一性检查 | G4: 公式=外键引用
A7: 2020-07-06 | B7: hzero | C7: 接口文档 | D7: hitf_document | E7: *document_id | F7: #interface_id | G7: #tenant_id | H7: document_name | I7: req_demo | J7: req_remark | K7: resp_success_status | L7: resp_success_mime_type | M7: resp_success_demo | N7: resp_failed_status | O7: resp_failed_mime_type | P7: resp_failed_demo | Q7: resp_remark | R7: remark | S7: req_mime_type | T7: req_raw_flag | U7: req_root_type | V7: resp_mime_type | W7: resp_raw_flag | X7: resp_root_type
E8: hitf_document-8 | F8: =接口配置!$E$10 | G8: 0 | H8: 发票查验接口默认文档
E9: hitf_document-9 | F9: =接口配置!$E$11 | G9: 0 | H9: 发票主数据采集接口默认文档
E10: hitf_document-10 | F10: =接口配置!$E$13 | G10: 0 | H10: 发票勾选结果查询接口默认文档
E11: hitf_document-11 | F11: =接口配置!$E$16 | G11: 0 | H11: 发票查验接口默认文档
E12: hitf_document-12 | F12: =接口配置!$E$19 | G12: 0 | H12: 发票勾选结果查询接口默认文档
A14: 2020-07-06 | B14: hzero | C14: 接口文档参数 | D14: hitf_document_param | E14: *param_id | F14: #document_id | G14: interface_id | H14: tenant_id | I14: #action_type | J14: mime_type | K14: param_type | L14: param_value_type | M14: #param_name | N14: default_value | O14: default_value_longtext | P14: required_flag | Q14: format_regexp | R14: value_demo | S14: parent_id | T14: level_path | U14: order_seq | V14: remark
A16: 2020-07-06 | B16: hzero | C16: 接口文档参数备选值 | D16: hitf_document_param_value | E16: *param_value_id | F16: #param_id | G16: document_id | H16: interface_id | I16: tenant_id | J16: default_flag | K16: #param_value | L16: remark

Sheet 应用类型定义
A1: 日期 | B1: 作者 | C1: 说明 | D1: 表
E4: *自动生成 | F4: #唯一性检查 | G4: 公式=外键引用
A7: 2020-07-06 | B7: hzero | C7: 应用产品配置 | D7: hitf_application | E7: *application_id | F7: #application_code | G7: application_name | H7: #tenant_id | I7: major_category | J7: minor_category | K7: compose_policy | L7: interface_id | M7: enabled_flag | N7: remark | O7: fast_fail_flag
E8: hitf_application-8 | F8: HIVC.INVOICE_CHECK | G8: 发票查验应用 | H8: 0 | I8: FINANCIAL | J8: INVOICE | K8: WEIGHT | L8: =接口配置!$E$10 | M8: 1 | O8: 1
E9: hitf_application-9 | F9: HIVC.INVOICE_TICK | G9: 发票勾选应用 | H9: 0 | I9: FINANCIAL | J9: INVOICE | K9: WEIGHT | L9: =接口配置!$E$12 | M9: 1 | O9: 1
E10: hitf_application-10 | F10: HIVC.INVOICE_TICK_RESULT | G10: 发票勾选结果查询应用 | H10: 0 | I10: FINANCIAL | J10: INVOICE | K10: WEIGHT | L10: =接口配置!$E$13 | M10: 1 | O10: 1
E11: hitf_application-11 | F11: HIVC.INVOICE_AUTH | G11: 发票认证应用 | H11: 0 | I11: FINANCIAL | J11: INVOICE | K11: ROUND_ROBIN | L11: =接口配置!$E$8 | M11: 1 | O11: 1
E12: hitf_application-12 | F12: HIVC.INVOICE_AUTH_RESULT | G12: 发票认证结果查询应用 | H12: 0 | I12: FINANCIAL | J12: INVOICE | K12: WEIGHT | L12: =接口配置!$E$9 | M12: 1 | O12: 1
E13: hitf_application-13 | F13: HIVC.INVOICE_META_DATA | G13: 发票主数据采集应用 | H13: 0 | I13: FINANCIAL | J13: INVOICE | K13: WEIGHT | L13: =接口配置!$E$11 | M13: 1 | O13: 1
A15: 2020-07-06 | B15: hzero | C15: 应用产品实例配置 | D15: hitf_application_inst | E15: *application_inst_id | F15: #application_id | G15: #tenant_id | H15: #inst_interface_id | I15: weight | J15: order_seq | K15: enabled_flag | L15: remark | M15: mapping_class
E16: hitf_application_inst-16 | F16: =应用类型定义!$E$8 | G16: 0 | H16: =接口配置!$E$16 | I16: 10 | J16: 1 | K16: 1 | L16: 航信接口 | M16: import org.hzero.boot.interfaces.sdk.dto.RequestPayloadDTO import org.hzero.boot.interfaces.sdk.dto.ResponsePayloadDTO import org.springframework.web.multipart.MultipartFile import java.util.HashMap import java.util.Map import org.hzero.boot.interfaces.sdk.log.LoggerDelegate import org.slf4j.Logger import java.text.SimpleDateFormat import com.fasterxml.jackson.annotation.JsonInclude import com.fasterxml.jackson.core.type.TypeReference import com.fasterxml.jackson.databind.ObjectMapper import org.apache.commons.lang3.StringUtils import org.hzero.core.base.BaseConstants /** * * 参数映射类 * */ class ParamReflect { static final Base64.Decoder DECODER = Base64.getDecoder() /** * 仅仅用于测试按钮，实际透传中此方法不会被调用，可不做任何实现。 * @return 用于测试的请求对象 */ public RequestPayloadDTO mockRequestPayloadDTO(){ /* * If you want to test the script for correctness, follow the example below to assign values * */ RequestPayloadDTO requestPayloadDTO = new RequestPayloadDTO(); // 请求头参数 Map<String, String> headerMap = new HashMap<>(2); requestPayloadDTO.setHeaderParamMap(headerMap); // 路径参数 Map<String, String> pathMap = new HashMap<>(2); requestPayloadDTO.setPathVariableMap(pathMap); // url参数 Map<String, String> requestMap = new HashMap<>(2); requestPayloadDTO.setRequestParamMap(requestMap); // 文件参数 Map<String, MultipartFile> file = new HashMap<>(2); requestPayloadDTO.setMultipartFileMap(file); // body媒体类型 requestPayloadDTO.setMediaType("application/json"); // json requestPayloadDTO.setPayload("{}"); return requestPayloadDTO; } /** * 仅仅用于测试按钮、实际透传中不会做任何特殊处理、可不做任何实现 * @return 用于测试的响应对象 */ public ResponsePayloadDTO mockResponsePayloadDTO(){ /* * If you want to test the script for correctness, follow the example below to assign values * */ ResponsePayloadDTO responsePayloadDTO = new ResponsePayloadDTO(); // 响应状态 responsePayloadDTO.setStatus("200"); // 响应消息 responsePayloadDTO.setMessage("正常"); // 目标接口响应消息的媒体类型 responsePayloadDTO.setMediaType("application/json"); // 目标接口响应消息 responsePayloadDTO.setPayload("{}"); return responsePayloadDTO; } /** * 在接口透传的时候 ，此方法的返回值将作为接口透传的请求参数 * * @param requestPayloadDTO 请求参数，此参数是被映射处理过后的参数 * @return */ RequestPayloadDTO requestDataConverter(RequestPayloadDTO requestPayloadDTO) { // 打印日志,测试按钮点击测试，日志信息将会展示到前端 Logger logger = LoggerDelegate.getLogger(); logger.debug("**************航信发票查验 入参 *************\n{}", requestPayloadDTO.toString()) //测试appCode:Z8nrPaEiA6olEuRPQAAcTlJofl4YRywOvyN3C0oi71k= String appcode = "Z8nrPaEiA6olEuRPQAAcTlJofl4YRywOvyN3C0oi71k=" ObjectMapper objectMapper = new ObjectMapper() Map<String, Object> requestPayload = objectMapper.readValue(requestPayloadDTO.getPayload(), new TypeReference<Map<String, Object>>() { }) Map<String, Object> data = new HashMap<>(6) data.put("nsrsbh", requestPayload.remove("buyerNo")) data.put("fpdm", requestPayload.remove("invoiceCode")) data.put("fphm", requestPayload.remove("invoiceNo")) data.put("kprq", requestPayload.remove("invoiceDate")) data.put("je", requestPayload.remove("invoiceAmount")) data.put("jym", requestPayload.remove("checkCode")) requestPayload.put("data", objectMapper.writeValueAsString(data)) requestPayload.put("appcode", appcode) logger.debug("**************航信发票查验 入参参映射结果 *************\n{}", requestPayloadDTO.toString()) requestPayloadDTO.setPayload(objectMapper.writeValueAsString(requestPayload)) return requestPayloadDTO } /** * 在接口透传结果处理的时候，此方法的返回结果将作为透传结果的返回值 * @param responsePayloadDTO 响应参数 * @return */ ResponsePayloadDTO responseDataConverter(ResponsePayloadDTO responsePayloadDTO) { Logger logger = LoggerDelegate.getLogger(); logger.debug("**************航信发票查验 *************\n{}", responsePayloadDTO.toString()) Map<String, String> VAT_INVOICE_TRANS_MAP = new HashMap<>(2) VAT_INVOICE_TRANS_MAP.put("buyerTaxNo", "buyerNo") VAT_INVOICE_TRANS_MAP.put("salerTaxNo", "salerNo") Map<String, String> LINE_TRANS_MAP = new HashMap<>(2) LINE_TRANS_MAP.put("detailAmount", "amount") LINE_TRANS_MAP.put("num", "quantity") Map<String, Object> resultMap = new HashMap<>(4) ObjectMapper objectMapper = new ObjectMapper() Map<String, Object> responsePayload = objectMapper.readValue(responsePayloadDTO.getPayload(), new TypeReference<Map<String, Object>>() { }) Map<String, String> codeMessage = (Map<String, String>) responsePayload.get("returnStateInfo") resultMap.put("code", codeMessage.get("returnCode")) resultMap.put("message", codeMessage.get("returnMessage")) if (codeMessage.get("returnCode").toString() != "0000") { responsePayloadDTO.setPayload(objectMapper.writeValueAsString(resultMap)) return responsePayloadDTO } String json = new String(DECODER.decode((String) responsePayload.get("data"))) Map<String, Object> result = objectMapper.readValue(json, new TypeReference<Map<String, Object>>() {}) List<Map<String, Object>> invoices = (List<Map<String, Object>>) result.get("invoiceList") Map<String, Object> invoice = invoices.get(0) Map<String, Object> invoiceInfo = (Map<String, Object>) invoice.get("invoiceInfo") resultMap.put("code", invoiceInfo.get("resultCode")) resultMap.put("message", invoiceInfo.get("resultTip")) Map<String, Object> responseMap = new HashMap<>() for (Map.Entry<String, Object> entry : invoiceInfo.entrySet()) { if (VAT_INVOICE_TRANS_MAP.containsKey(entry.getKey())) { responseMap.put(VAT_INVOICE_TRANS_MAP.get(entry.getKey()), entry.getValue()) } else { if (StringUtils.isNotEmpty((String) entry.getValue())) { responseMap.put(entry.getKey(), entry.getValue()) } } } SimpleDateFormat formatter = new SimpleDateFormat(BaseConstants.Pattern.NONE_DATE) Date newDate= formatter.parse((String) responseMap.get("invoiceDate")) formatter = new SimpleDateFormat(BaseConstants.Pattern.DATE) responseMap.put("invoiceDate", formatter.format(newDate)) resultMap.put("data", responseMap) List<Map<String, Object>> items; if (invoiceInfo.get("resultCode").toString() == "0001") { items = (List<Map<String, Object>>) invoiceInfo.remove("detailList") for (Map<String, Object> item : items) { item.put("amount", item.remove("detailAmount")) item.put("quantity", item.remove("num")) if (item.containsKey("taxRate") && !item.get("taxRate").toString().contains("%")) { item.put("taxAmount",BigDecimal.ZERO) } } responseMap.put("lines", items) } objectMapper.setSerializationInclusion(JsonInclude.Include.NON_EMPTY) responsePayloadDTO.setPayload(objectMapper.writeValueAsString(resultMap)) logger.debug("**************航信发票查验 响应参映射结果 *************\n{}", responsePayloadDTO.toString()) return responsePayloadDTO } }
E17: hitf_application_inst-17 | F17: =应用类型定义!$E$9 | G17: 0 | H17: =接口配置!$E$18 | I17: 10 | J17: 1 | K17: 1 | L17: 航信接口
E18: hitf_application_inst-18 | F18: =应用类型定义!$E$10 | G18: 0 | H18: =接口配置!$E$19 | I18: 10 | J18: 1 | K18: 1 | L18: 航信接口
E19: hitf_application_inst-19 | F19: =应用类型定义!$E$11 | G19: 0 | H19: =接口配置!$E$14 | I19: 1 | J19: 10 | K19: 1 | L19: 航信接口
E20: hitf_application_inst-20 | F20: =应用类型定义!$E$12 | G20: 0 | H20: =接口配置!$E$15 | I20: 10 | J20: 1 | K20: 1 | L20: 航信接口
E21: hitf_application_inst-21 | F21: =应用类型定义!$E$13 | G21: 0 | H21: =接口配置!$E$17 | I21: 10 | J21: 1 | K21: 1 | L21: 航信接口
A23: 2020-07-06 | B23: hzero | C23: 应用产品实例参数映射 | D23: hitf_application_inst_map | E23: *application_inst_map_id | F23: #application_inst_id | G23: application_id | H23: tenant_id | I23: #action_type | J23: #source_param_id | K23: target_param_id | L23: remark
