Workbook

Sheet README
C1: 注意这个文档不能 merge！！ 发现冲突以后，先备份自己的改动，然后更新到最新版，然后再添加新的数据。
C3: 正式的数据从第二个 sheet 页开始,每页 从 D7 单元格开始有效 同一个表的数据要连续,中间不能有空行 Sheet 页的名字不要包含空格,中文等 | E3: 颜色示例(非必须,非强制)
C4: 请给特殊单元格,列名添加颜色,提高数据可读性 | E4: *自动生成 | F4: #唯一性检查 | G4: 公式=外键引用
C5: 理论上,表的前后顺序,sheet 页的顺序没有严格要求,但请尽量按照先插 后引用的顺序排列,减少迭代次数!
C7: 列名格式举例 | D7: 说明 | E7: 备注
C8: ROLE_CODE | D8: 普通
C9: *USER_ID | D9: *前置, 该列的值自动生成,当数据库存在等价记录时,这个值会被替换为数据库中已存在的值 | E9: 自增长(或序列)主键列. 当不作为外键引用时,一般写* 作为外键时,写可读的值 | F9: 目前 oracle 是序列,其他自增涨
C10: #USER_NAME | D10: #前置,表中所有带有#的列组成一个唯一性校验,在执行插入之前,会首先按照唯一键来检查数据库是否存在等价记录 | E10: 可以有多列.仅支持数字,字符串 当#列涉及到公式时,会先确定公式的值
C11: UNIT_PRICE(DECIMAL) | D11: (TYPE)指定这一列的类型,默认会自动检测: _ID结尾为数字; _DATE 结尾为日期; 其他默认为VARCHAR | E11: 一般不需要指定. 日期格式仅支持: yyyy-MM-dd HH:mm:ss yyyy-MM-dd
C12: ROLE_NAME:zh_CN | D12: :LANG 指定语言环境 | E12: TL 表数据不需要专门写
C15: 外键引用(公式) | D15: 用于引用外键,也可用于普通值 目前不支持特别复杂的公式 | E15: 自动增长列,如果被公式引用,最好写一个人可以读懂的值,增强公式可读性
C18: 关于公式的说明
C19: 一般用于引用自动生成的外键.所有公式均为 Excel 支持的标准公式,但不支持特别复杂的计算公式,比如范围计算
C20: E9 | D20: 相对引用当前页 E9 单元格
C21: $E$9 | D21: 绝对引用当前页 E9 单元格
C22: RESOURCE!E23 | D22: 引用 RESOURCE 页的 E23 单元格(相对)
C23: RESOURCE!$E$23 | D23: 引用 RESOURCE 页的 E23 单元格(绝对)
C25: 关于相对引用 | D25: 举例:当 F10 单元格引用 A9 时 将 F10 的复制到 F11 单元格时, F11 引用的是 A10 将 F10 的复制到 G11 时, G11 实际引用的是 B10 以上情况适用于拖拽填充
C26: 关于绝对引用 | D26: 复制公式单元格时,保持公式不变
C27: 相对引用,绝对引用各有用途. 直接拖拽填充就可以避免大量重复工作

Sheet 值集数据
A1: 日期 | B1: 作者 | C1: 说明 | D1: 表
E4: *自动生成 | F4: #唯一性检查 | G4: 公式=外键引用
A7: 2020-04-21 | B7: hzero | C7: LOV表 | D7: hpfm_lov | E7: *lov_id | F7: #lov_code | G7: lov_type_code | H7: route_name | I7: lov_name:zh_CN | J7: lov_name:en_US | K7: description:zh_CN | L7: description:en_US | M7: #tenant_id | N7: parent_lov_code | O7: parent_tenant_id | P7: custom_sql | Q7: custom_url | R7: value_field | S7: display_field | T7: must_page_flag | U7: enabled_flag | V7: translation_sql
E8: hpfm_lov-41 | F8: HITF.APPLICATION.CLIENT | G8: SQL | H8: hpfm | I8: 应用配置选择客户端 | J8: 应用配置选择客户端 | K8: 接口平台应用配置选择oauth客户端 | M8: 0 | P8: SELECT oc.id oauth_client_id, oc.name client_name FROM oauth_client oc WHERE 1 = 1 <if test="tenantId != null and tenantId != ''"> AND oc.organization_id IN ( #{tenantId}, 0 ) </if> <if test="clientName!= null and clientName!= ''"> <bind name="clientNameLike" value="'%' + clientName+ '%'"/> AND oc.name LIKE #{clientNameLike} </if> | T8: 1 | U8: 1 | X8: =#REF! -> #REF!
E9: hpfm_lov-42 | F9: HITF.APPLICATION.SERVER_UNUSE | G9: URL | H9: hitf | I9: 应用配置获取未绑定的服务 | J9: 应用配置获取未绑定的服务 | K9: 获取未绑定的服务列表 | L9: 获取未绑定的服务列表 | M9: 0 | Q9: /v1/{organizationId}/interface-servers/{applicationId}/servers/not-assign | R9: value | S9: meaning | T9: 1 | U9: 1
E10: hpfm_lov-43 | F10: HITF.AUTH_TYPE | G10: IDP | I10: 认证模式 | J10: 认证模式 | M10: 0 | T10: 1 | U10: 1
E11: hpfm_lov-44 | F11: HITF.GRANT_TYPE | G11: IDP | I11: 授权模式 | J11: 授权模式 | M11: 0 | T11: 1 | U11: 1
E12: hpfm_lov-45 | F12: HITF.INTERFACE_STATUS | G12: IDP | I12: 接口状态 | J12: 接口状态 | M12: 0 | T12: 1 | U12: 1
E13: hpfm_lov-46 | F13: HITF.REQUEST_HEADER | G13: IDP | I13: 接口ContentType | J13: 接口ContentType | M13: 0 | T13: 1 | U13: 1
E14: hpfm_lov-47 | F14: HITF.REQUEST_METHOD | G14: IDP | I14: 请求方式 | J14: 请求方式 | M14: 0 | T14: 1 | U14: 1
E15: hpfm_lov-48 | F15: HITF.SERVICE_TYPE | G15: IDP | I15: 服务类型 | J15: 服务类型 | M15: 0 | T15: 1 | U15: 1
E16: hpfm_lov-49 | F16: HITF.SOAP_VERSION | G16: IDP | I16: SOAP版本 | J16: SOAP版本 | M16: 0 | T16: 1 | U16: 1
E17: hpfm_lov-50 | F17: HITF.SOAP_WSS_PASSWORD_TYPE | G17: IDP | I17: SOAP加密类型 | J17: SOAP加密类型 | M17: 0 | T17: 1 | U17: 1
E18: hpfm_lov-137 | F18: HITF.MIME_TYPE | G18: IDP | I18: MIME类型 | J18: MIME类型 | K18: MIME类型 | L18: MIME类型 | M18: 0 | T18: 0 | U18: 1
E19: hpfm_lov-138 | F19: HITF.PARAM_TYPE | G19: IDP | I19: 参数类型 | J19: 参数类型 | K19: 参数类型 | L19: 参数类型 | M19: 0 | T19: 1 | U19: 1
E20: hpfm_lov-139 | F20: HITF.PARAM_VALUE_TYPE | G20: IDP | I20: 参数值类型 | J20: 参数值类型 | K20: 参数值类型 | L20: 参数值类型 | M20: 0 | T20: 1 | U20: 1
E21: hpfm_lov-140 | F21: HITF.HTTP_ACTION_TYPE | G21: IDP | I21: HTTP操作类型 | J21: HTTP操作类型 | M21: 0 | T21: 1 | U21: 1
E22: hpfm_lov-141 | F22: HITF.HTTP_HEADER | G22: IDP | I22: 请求头参数 | J22: 请求头参数 | M22: 0 | T22: 1 | U22: 1
E23: hpfm_lov-143 | F23: HITF.CONTENT_TYPE | G23: IDP | I23: 请求内容类型 | J23: 请求内容类型 | M23: 0 | T23: 1 | U23: 1
E24: hpfm_lov-144 | F24: HITF.RAW_MIME_TYPE | G24: IDP | I24: raw类型的可选类型 | J24: raw类型的可选类型 | M24: 0 | T24: 1 | U24: 1
E25: hpfm_lov-147 | F25: HITF.ROOT_TYPE | G25: IDP | I25: 根节点类型 | J25: 根节点类型 | M25: 0 | T25: 1 | U25: 1
E26: hpfm_lov-148 | F26: HITF.STATISTICS_LEVEL | G26: IDP | I26: 调用统计维度 | J26: 调用统计维度 | M26: 0 | T26: 1 | U26: 1
E27: hpfm_lov-149 | F27: HITF.STATISTICS_PERIOD | G27: IDP | I27: 宽免周期 | J27: 宽免周期 | M27: 0 | T27: 1 | U27: 1
E28: hpfm_lov-150 | F28: HITF.EXCEED_THRESHOLD_ACTION | G28: IDP | I28: 超阈值措施 | J28: 超阈值措施 | M28: 0 | T28: 1 | U28: 1
E29: hpfm_lov-151 | F29: HITF.USE_CASE | G29: URL | H29: hitf | I29: 接口平台测试用例 | J29: 接口平台测试用例 | M29: 0 | Q29: /v1/{organizationId}/{interfaceId}/usecases?usecaseType=HEALTH-CHECK | R29: interfaceUsecaseId | S29: usecaseName | T29: 1 | U29: 1
E30: hpfm_lov-152 | F30: HITF.INVOKE_TYPE | G30: IDP | I30: 接口请求类型 | J30: 接口请求类型 | M30: 0 | T30: 1 | U30: 1
E31: hpfm_lov-153 | F31: HITF.CODE_TYPE | G31: IDP | I31: 预览代码类型 | J31: 预览代码类型 | M31: 0 | R31: value | S31: meaning | T31: 1 | U31: 1
E32: hpfm_lov-155 | F32: HITF.PARAM_VALUE | G32: SQL | H32: hitf | I32: 参数可选列表 | J32: 参数可选列表 | M32: 0 | P32: select hdpv.param_value FROM hitf_document_param_value hdpv where hdpv.tenant_id = #{tenantId} and hdpv.interface_id = #{interfaceId} and hdpv.document_id = #{documentId} and hdpv.param_id = #{paramId} | R32: paramValue | S32: paramValue | T32: 1 | U32: 1
E33: hpfm_lov-156 | F33: HITF.AUTH_LEVEL | G33: IDP | I33: 认证层级 | J33: 认证层级 | M33: 0 | T33: 1 | U33: 1
E34: hpfm_lov-157 | F34: HITF.USECASE_TYPE | G34: IDP | I34: 测试用例类型 | J34: 测试用例类型 | M34: 0 | T34: 1 | U34: 1
E35: hpfm_lov-159 | F35: HITF.ROLE.AUTHORIZABLE | G35: URL | H35: hitf | I35: 角色可授权权限集 | J35: 角色可授权权限集 | M35: 0 | Q35: /v1/{organizationId}/client-roles/{roleId}/authorizable | T35: 1 | U35: 1
E36: hpfm_lov-162 | F36: HITF.DOCUMENT_PARAM | G36: SQL | H36: hitf | I36: 文档参数 | J36: 文档参数 | M36: 0 | P36: select param_id as parameter_id, param_name, default_value, default_value_longtext from hitf_document_param where 1=1 and document_id = #{documentId} and interface_id = #{interfaceId} <if test="tenantId!=null"> and tenant_id = #{tenantId} </if> <if test="paramName!=null and paramName!=''"> <bind name="paramNameLike" value="'%'+paramName+'%'"></bind> and param_name like #{paramNameLike} </if> | R36: parameterId | S36: paramName | T36: 1 | U36: 1
E37: hpfm_lov-181 | F37: HITF.SITE.USE_CASE | G37: URL | H37: hitf | I37: 测试用例(平台级调用) | J37: 测试用例(平台级调用) | M37: 0 | Q37: /v1/{interfaceId}/usecases?usecaseType=HEALTH-CHECK | T37: 1 | U37: 1
E38: hpfm_lov-189 | F38: HITF.SERVICE_CATEGORY | G38: IDP | I38: 服务类别 | J38: 服务类别 | M38: 0 | T38: 1 | U38: 1
E39: hpfm_lov-190 | F39: HITF.PASSWORD_ENCODE_TYPE | G39: IDP | I39: 密码加密类型 | J39: 密码加密类型 | M39: 0 | T39: 1 | U39: 1
E40: hpfm_lov-191 | F40: HITF.APP_MAJOR_CATEGORY | G40: IDP | I40: 应用大类 | J40: 应用大类 | M40: 0 | T40: 1 | U40: 1
E41: hpfm_lov-192 | F41: HITF.APP_MINOR_CATEGORY | G41: IDP | I41: 应用小类 | J41: 应用小类 | M41: 0 | N41: HITF.APP_MAJOR_CATEGORY | O41: 0 | T41: 1 | U41: 1
E42: hpfm_lov-194 | F42: HITF.COMPOSE_POLICY | G42: IDP | I42: 组合策略 | J42: 组合策略 | M42: 0 | T42: 1 | U42: 1
E43: hpfm_lov-195 | F43: HITF.COMPOSE_ENTRY_INTERFACE | G43: SQL | H43: hitf | I43: 组合接口 | J43: 组合接口 | M43: 0 | P43: select hi.interface_id, hi.interface_code, hi.interface_name, his.server_code, his.server_name, ht.tenant_name from hitf_interface hi join hitf_interface_server his on hi.interface_server_id = his.interface_server_id left join hpfm_tenant ht on hi.tenant_id = ht.tenant_id where his.service_category = 'COMPOSITE' and his.enabled_flag = 1 <if test="interfaceCode!=null and interfaceCode!=''"> <bind name="interfaceCodeLike" value="'%'+interfaceCode+'%'"></bind> and hi.interface_code like #{interfaceCodeLike} </if> <if test="interfaceName!=null and interfaceName!=''"> <bind name="interfaceNameLike" value="'%'+interfaceName+'%'"></bind> and hi.interface_name like #{interfaceNameLike} </if> | R43: interfaceId | S43: interfaceName | T43: 1 | U43: 1
E44: hpfm_lov-196 | F44: HITF.COMPOSE_INST_INTERFACE | G44: SQL | H44: hitf | I44: 实例接口 | J44: 实例接口 | M44: 0 | P44: select hi.interface_id as inst_interface_id, hi.interface_code, hi.interface_name, his.server_code, his.server_name, ht.tenant_name from hitf_interface hi join hitf_interface_server his on hi.interface_server_id = his.interface_server_id left join hpfm_tenant ht on hi.tenant_id = ht.tenant_id where his.service_category != 'COMPOSITE' and his.enabled_flag = 1 <if test="interfaceCode!=null and interfaceCode!=''"> <bind name="interfaceCodeLike" value="'%'+interfaceCode+'%'"></bind> and hi.interface_code like #{interfaceCodeLike} </if> <if test="interfaceName!=null and interfaceName!=''"> <bind name="interfaceNameLike" value="'%'+interfaceName+'%'"></bind> and hi.interface_name like #{interfaceNameLike} </if> | R44: instInterfaceId | S44: interfaceCode | T44: 1 | U44: 1
E45: hpfm_lov-197 | F45: HITF.PARAMETER_MAPPING | G45: SQL | H45: hitf | I45: 参数映射 | J45: 参数映射 | M45: 0 | P45: SELECT h.param_id, h.param_name, h.param_type, h.action_type from hitf_document_param h where 1=1 <choose> <when test="paramType!=null and paramType=='BODY'"> and h.param_type = 'BODY' </when> <otherwise> and h.param_type!='BODY' </otherwise> </choose> <if test="actionType!=null and actionType!=''"> and h.action_type = #{actionType} </if> <if test="instInterfaceId!=null"> and h.interface_id = #{instInterfaceId} </if> | R45: paramId | S45: paramName | T45: 1 | U45: 1
E46: hpfm_lov-232 | F46: HITF.HTTP_CONFIG_PROPERTY | G46: IDP | I46: HTTP配置 | J46: HTTP配置 | M46: 0 | T46: 1 | U46: 1
E47: hpfm_lov-234 | F47: HITF.IMPORT_STATUS | G47: IDP | I47: 导入历史状态 | J47: 导入历史状态 | M47: 0 | T47: 1 | U47: 1
E48: hpfm_lov-246 | F48: HITF.COMPOSE_SERVER | G48: SQL | H48: hivc | I48: 组合服务 | J48: 组合服务 | M48: 0 | P48: <bind name="organizationId" value="@io.choerodon.core.oauth.DetailsHelper@getUserDetails().getOrganizationId()"/> select his.interface_server_id, his.server_code, his.server_name from hitf_interface_server his where his.service_category = 'COMPOSITE' and his.tenant_id = #{organizationId} and his.enabled_flag = 1 <if test="serverCode!=null and serverCode!=''"> <bind name="serverCodeLike" value="'%'+serverCode+'%'"></bind> and his.server_code like #{serverCodeLike} </if> <if test="serverName!=null and serverName!=''"> <bind name="serverNameLike" value="'%'+serverName+'%'"></bind> and his.server_name like #{serverNameLike} </if> | T48: 1 | U48: 1
E49: hpfm_lov-247 | F49: HITF.COMPOSE_INTERFACE | G49: SQL | H49: hivc | I49: 组合接口 | J49: 组合接口 | M49: 0 | P49: <bind name="organizationId" value="@io.choerodon.core.oauth.DetailsHelper@getUserDetails().getOrganizationId()"/> select hi.interface_id, hi.interface_code, hi.interface_name from hitf_interface hi join hitf_interface_server his on hi.interface_server_id = his.interface_server_id where his.server_code = #{serverCode} and hi.tenant_id = #{organizationId} <if test="interfaceCode!=null and interfaceCode!=''"> <bind name="interfaceCodeLike" value="'%'+interfaceCode+'%'"></bind> and hi.interface_code like #{interfaceCodeLike} </if> <if test="interfaceName!=null and interfaceName!=''"> <bind name="interfaceNameLike" value="'%'+interfaceName+'%'"></bind> and hi.interface_name like #{interfaceNameLike} </if> | T49: 1 | U49: 1
E50: hpfm_lov-265 | F50: HITF.SETTLEMENT_PERIOD | G50: IDP | I50: 结算周期 | J50: 结算周期 | M50: 0 | T50: 1 | U50: 1
E51: hpfm_lov-266 | F51: HITF.CHARGE_SET_STATUS | G51: IDP | I51: 服务及接口计费设置状态 | J51: 服务及接口计费设置状态 | M51: 0 | T51: 1 | U51: 1
E52: hpfm_lov-267 | F52: HITF.CHARGE_GROUP_STATUS | G52: IDP | I52: 组合计费设置状态 | J52: 组合计费设置状态 | M52: 0 | T52: 1 | U52: 1
E53: hpfm_lov-268 | F53: HITF.GROUP_SERVER_TYPE | G53: IDP | I53: 组合计费服务类型 | J53: 组合计费服务类型 | M53: 0 | T53: 1 | U53: 1
E54: hpfm_lov-269 | F54: HITF.PURCHASE_TYPE | G54: IDP | I54: 计费用户购买类型 | J54: 计费用户购买类型 | M54: 0 | T54: 1 | U54: 1
E55: hpfm_lov-270 | F55: HITF.AVAILABLE_STATUS | G55: IDP | I55: 服务可用状态 | J55: 服务可用状态 | M55: 0 | T55: 1 | U55: 1
E56: hpfm_lov-271 | F56: HITF.CHARGE_INTERFACE | G56: SQL | H56: hitf | I56: 接口计费可用接口 | J56: 接口平台接口 | M56: 0 | P56: select hi.interface_id, hi.interface_code, hi.interface_name from hitf_interface hi join hitf_interface_server his on hi.interface_server_id = his.interface_server_id where his.server_code = #{serverCode} AND hi.interface_id NOT IN ( SELECT hcsh.interface_id FROM hitf_charge_set_header hcsh join hitf_interface_server hisl on hcsh.interface_server_id = hisl.interface_server_id WHERE hcsh.type_code = 'INTERFACE' and hisl.server_code = his.server_code ) AND his.interface_server_id NOT IN ( SELECT hcgl.interface_id FROM hitf_charge_group_line hcgl join hitf_interface_server hisl on hcgl.interface_server_id = hisl.interface_server_id WHERE hcgl.type_code = 'INTERFACE' and hisl.server_code = his.server_code ) <if test="interfaceCode!=null and interfaceCode!=''"> <bind name="interfaceCodeLike" value="'%'+interfaceCode+'%'"></bind> and hi.interface_code like #{interfaceCodeLike} </if> <if test="interfaceName!=null and interfaceName!=''"> <bind name="interfaceNameLike" value="'%'+interfaceName+'%'"></bind> and hi.interface_name like #{interfaceNameLike} </if> | T56: 1 | U56: 1
E57: hpfm_lov-276 | F57: HITF.CHARGE_SERVER | G57: SQL | H57: hitf | I57: 接口计费可用服务 | J57: 接口计费可用服务 | M57: 0 | P57: SELECT his.interface_server_id, his.server_code, his.server_name FROM hitf_interface_server his WHERE his.enabled_flag = 1 AND his.interface_server_id NOT IN ( SELECT hcsh.interface_server_id FROM hitf_charge_set_header hcsh WHERE hcsh.type_code = 'SERVER' ) AND his.interface_server_id NOT IN ( SELECT hcgl.interface_server_id FROM hitf_charge_group_line hcgl WHERE hcgl.type_code = 'SERVER' ) AND EXISTS ( SELECT 1 FROM hitf_interface hi WHERE hi.interface_server_id = his.interface_server_id AND hi.enabled_flag = 1 ) <if test="serverCode!=null and serverCode!=''"> <bind name="serverCodeLike" value="'%'+serverCode+'%'"></bind> and his.server_code like #{serverCodeLike} </if> <if test="serverName!=null and serverName!=''"> <bind name="serverNameLike" value="'%'+serverName+'%'"></bind> and his.server_name like #{serverNameLike} </if> | T57: 1 | U57: 1
E58: hpfm_lov-282 | F58: HITF.SVC.EXPRESSION_TYPE | G58: IDP | I58: 表达式类型 | J58: 表达式类型 | K58: 表达式类型 | L58: 表达式类型 | M58: 0 | T58: 1 | U58: 1
E59: hpfm_lov-283 | F59: HITF.SVC.COL_TYPE | G59: IDP | I59: 属性字段类型 | J59: 属性字段类型 | K59: 属性字段类型 | L59: 属性字段类型 | M59: 0 | T59: 1 | U59: 1
E60: hpfm_lov-284 | F60: HITF.SVC.MODEL_OPERATOR | G60: IDP | I60: 操作符 | J60: 操作符 | K60: 操作符 | L60: 操作符 | M60: 0 | T60: 1 | U60: 1
E61: hpfm_lov-285 | F61: HITF.SVC.PRIVACY_LEVEL | G61: IDP | I61: 隐私级别 | J61: 隐私级别 | K61: 隐私级别 | L61: 隐私级别 | M61: 0 | T61: 1 | U61: 1
E62: hpfm_lov-286 | F62: HITF.SVC.PARAM_TYPE | G62: IDP | I62: 参数类型 | J62: Parameter type | K62: 参数类型 | L62: Parameter type | M62: 0 | T62: 1 | U62: 1
E63: hpfm_lov-287 | F63: HITF.PROTOCOL | G63: IDP | I63: 协议 | J63: protocol | M63: 0 | T63: 1 | U63: 1
E64: hpfm_lov-292 | F64: HITF.DATASOURCE | G64: SQL | H64: hpfm | I64: 数据源选择 | J64: 数据源选择 | K64: 接口平台数据源选择 | L64: 接口平台数据源选择 | M64: 0 | P64: select datasource_id, ds_purpose_code, db_type, datasource_code, tenant_id, description from hpfm_datasource where enabled_flag = 1 and ds_purpose_code = 'DITF' <if test="datasourceCode!=null and datasourceCode!=''"> <bind name="datasourceCodeLike" value="'%'+datasourceCode+'%'"></bind> and datasource_code like #{datasourceCodeLike} </if> <if test="description!=null and description!=''"> <bind name="descriptionLike" value="'%'+description+'%'"></bind> and description like #{descriptionLike} </if> | T64: 1 | U64: 1
E65: hpfm_lov-293 | F65: HITF.INTERFACE_LOG.CLEAR_TYPE | G65: IDP | I65: 接口调用信息清理类型 | J65: 接口调用信息清理类型 | K65: 接口调用信息清理类型 | L65: 接口调用信息清理类型 | M65: 0 | T65: 1 | U65: 1
E66: hpfm_lov-294 | F66: HITF.CONSUMER_TYPE | G66: IDP | I66: 队列消费者类型 | J66: 队列消费者类型 | M66: 0 | T66: 1 | U66: 1
E67: hpfm_lov-295 | F67: HITF.STRCTURE.LINE.FILED_TYPE | G67: IDP | I67: 字段类型 | J67: 字段类型 | K67: 字段类型 | L67: Field Type | M67: 0 | T67: 1 | U67: 1
E68: hpfm_lov-296 | F68: HITF.STRUCTURE_CATEGORY | G68: IDP | I68: 结构分类 | J68: 结构分类 | K68: 结构分类 | L68: 结构分类 | M68: 0 | T68: 1 | U68: 1
E69: hpfm_lov-297 | F69: HITF.STRCTURE.LINE.BIZ_USAGE | G69: IDP | I69: 业务用途 | J69: 业务用途 | K69: test | L69: test12345 | M69: 0 | T69: 1 | U69: 1
E70: hpfm_lov-298 | F70: HITF.STRCTURE.COMPOSITION | G70: IDP | I70: 构建方式 | J70: 构建方式 | M70: 0 | T70: 1 | U70: 1
A72: 2020-04-21 | B72: hzero | C72: LOV独立值集表 | D72: hpfm_lov_value | E72: *lov_value_id | F72: #lov_id | G72: lov_code | H72: #value | I72: meaning:zh_CN | J72: meaning:en_US | K72: description:zh_CN | L72: description:en_US | M72: #tenant_id | N72: tag | O72: order_seq | P72: #parent_value | Q72: start_date_active(DATE) | R72: end_date_active(DATE) | S72: enabled_flag
E73: * | F73: =值集数据!$E$10 -> hpfm_lov-43 | G73: HITF.AUTH_TYPE | H73: NONE | I73: NONE | J73: NONE | M73: 0 | O73: 1 | S73: 1
E74: * | F74: =值集数据!$E$10 -> hpfm_lov-43 | G74: HITF.AUTH_TYPE | H74: BASIC | I74: BASIC | J74: BASIC | M74: 0 | O74: 2 | S74: 1
E75: * | F75: =值集数据!$E$10 -> hpfm_lov-43 | G75: HITF.AUTH_TYPE | H75: OAUTH2 | I75: OAUTH2 | J75: OAUTH2 | M75: 0 | O75: 3 | S75: 1
E76: * | F76: =值集数据!$E$11 -> hpfm_lov-44 | G76: HITF.GRANT_TYPE | H76: CLIENT | I76: CLIENT | J76: CLIENT | M76: 0 | O76: 1 | S76: 1
E77: * | F77: =值集数据!$E$11 -> hpfm_lov-44 | G77: HITF.GRANT_TYPE | H77: PASSWORD | I77: PASSWORD | J77: PASSWORD | M77: 0 | O77: 2 | S77: 1
E78: * | F78: =值集数据!$E$12 -> hpfm_lov-45 | G78: HITF.INTERFACE_STATUS | H78: ENABLED | I78: 正常 | J78: 正常 | M78: 0 | O78: 1 | S78: 1
E79: * | F79: =值集数据!$E$12 -> hpfm_lov-45 | G79: HITF.INTERFACE_STATUS | H79: DISABLED | I79: 失效 | J79: 失效 | M79: 0 | O79: 2 | S79: 1
E80: * | F80: =值集数据!$E$12 -> hpfm_lov-45 | G80: HITF.INTERFACE_STATUS | H80: DISABLED_INPROGRESS | I80: 待失效(窗口期:30天) | J80: 待失效(窗口期:30天) | M80: 0 | O80: 3 | S80: 1
E81: * | F81: =值集数据!$E$13 -> hpfm_lov-46 | G81: HITF.REQUEST_HEADER | H81: application/json | I81: application/json | J81: application/json | M81: 0 | O81: 1 | S81: 1
E82: * | F82: =值集数据!$E$13 -> hpfm_lov-46 | G82: HITF.REQUEST_HEADER | H82: application/xml | I82: application/xml | J82: application/xml | M82: 0 | O82: 2 | S82: 1
E83: * | F83: =值集数据!$E$14 -> hpfm_lov-47 | G83: HITF.REQUEST_METHOD | H83: GET | I83: GET | J83: GET | M83: 0 | O83: 1 | S83: 1
E84: * | F84: =值集数据!$E$14 -> hpfm_lov-47 | G84: HITF.REQUEST_METHOD | H84: POST | I84: POST | J84: POST | M84: 0 | O84: 2 | S84: 1
E85: * | F85: =值集数据!$E$14 -> hpfm_lov-47 | G85: HITF.REQUEST_METHOD | H85: PUT | I85: PUT | J85: PUT | M85: 0 | O85: 3 | S85: 1
E86: * | F86: =值集数据!$E$14 -> hpfm_lov-47 | G86: HITF.REQUEST_METHOD | H86: DELETE | I86: DELETE | J86: DELETE | M86: 0 | O86: 4 | S86: 1
E87: * | F87: =值集数据!$E$15 -> hpfm_lov-48 | G87: HITF.SERVICE_TYPE | H87: REST | I87: REST | J87: REST | M87: 0 | O87: 1 | S87: 1
E88: * | F88: =值集数据!$E$15 -> hpfm_lov-48 | G88: HITF.SERVICE_TYPE | H88: SOAP | I88: SOAP | J88: SOAP | M88: 0 | O88: 2 | S88: 1
E89: * | F89: =值集数据!$E$16 -> hpfm_lov-49 | G89: HITF.SOAP_VERSION | H89: SOAP11 | I89: SOAP11 | J89: SOAP11 | M89: 0 | O89: 1 | S89: 1
E90: * | F90: =值集数据!$E$16 -> hpfm_lov-49 | G90: HITF.SOAP_VERSION | H90: SOAP12 | I90: SOAP12 | J90: SOAP12 | M90: 0 | O90: 2 | S90: 1
E91: * | F91: =值集数据!$E$18 -> hpfm_lov-137 | G91: HITF.MIME_TYPE | H91: form-data | I91: multipart/form-data | J91: multipart/form-data | M91: 0 | O91: 1 | S91: 1
E92: * | F92: =值集数据!$E$18 -> hpfm_lov-137 | G92: HITF.MIME_TYPE | H92: x-www-form-urlencoded | I92: application/x-www-form-urlencoded | J92: application/x-www-form-urlencoded | M92: 0 | O92: 2 | S92: 1
E93: * | F93: =值集数据!$E$18 -> hpfm_lov-137 | G93: HITF.MIME_TYPE | H93: xml | I93: text/xml | J93: text/xml | M93: 0 | O93: 3 | S93: 1
E94: * | F94: =值集数据!$E$18 -> hpfm_lov-137 | G94: HITF.MIME_TYPE | H94: json | I94: application/json | J94: application/json | M94: 0 | O94: 4 | S94: 1
E95: * | F95: =值集数据!$E$19 -> hpfm_lov-138 | G95: HITF.PARAM_TYPE | H95: HEADER | I95: 头部参数 | J95: 头部参数 | M95: 0 | O95: 1 | S95: 1
E96: * | F96: =值集数据!$E$19 -> hpfm_lov-138 | G96: HITF.PARAM_TYPE | H96: GET | I96: 查询参数 | J96: 查询参数 | M96: 0 | O96: 2 | S96: 1
E97: * | F97: =值集数据!$E$19 -> hpfm_lov-138 | G97: HITF.PARAM_TYPE | H97: PATH | I97: 路径参数 | J97: 路径参数 | M97: 0 | O97: 3 | S97: 1
E98: * | F98: =值集数据!$E$19 -> hpfm_lov-138 | G98: HITF.PARAM_TYPE | H98: BODY | I98: 请求体/响应体 | J98: 请求体/响应体 | M98: 0 | O98: 4 | S98: 1
E99: * | F99: =值集数据!$E$20 -> hpfm_lov-139 | G99: HITF.PARAM_VALUE_TYPE | H99: STRING | I99: 字符串 | J99: STRING | M99: 0 | O99: 1 | S99: 1
E100: * | F100: =值集数据!$E$20 -> hpfm_lov-139 | G100: HITF.PARAM_VALUE_TYPE | H100: ARRAY | I100: 数组 | J100: ARRAY | M100: 0 | O100: 2 | S100: 1
E101: * | F101: =值集数据!$E$20 -> hpfm_lov-139 | G101: HITF.PARAM_VALUE_TYPE | H101: OBJECT | I101: 对象 | J101: OBJECT | M101: 0 | O101: 3 | S101: 1
E102: * | F102: =值集数据!$E$21 -> hpfm_lov-140 | G102: HITF.HTTP_ACTION_TYPE | H102: REQ | I102: 请求 | J102: 请求 | M102: 0 | O102: 1 | S102: 1
E103: * | F103: =值集数据!$E$21 -> hpfm_lov-140 | G103: HITF.HTTP_ACTION_TYPE | H103: RESP | I103: 响应 | J103: 响应 | M103: 0 | O103: 2 | S103: 1
E104: * | F104: =值集数据!$E$22 -> hpfm_lov-141 | G104: HITF.HTTP_HEADER | H104: Authorization | I104: Authorization | J104: Authorization | M104: 0 | O104: 1 | S104: 1
E105: * | F105: =值集数据!$E$22 -> hpfm_lov-141 | G105: HITF.HTTP_HEADER | H105: Cache-Control | I105: Cache-Control | J105: Cache-Control | M105: 0 | O105: 2 | S105: 1
...
